{
  "name": "Dutch Merchant Ship Names from Greek Mythology (Creatures)",
  "formula": "1d8",
  "description": "",
  "results": [
    {
      "range": [
        1,
        1
      ],
      "description": "Centaur",
      "_id": "HHp97nAw811hhyRt",
      "type": "text",
      "name": "",
      "img": null,
      "weight": 1,
      "drawn": false,
      "flags": {},
      "_stats": {
        "compendiumSource": null,
        "duplicateSource": null,
        "exportSource": null,
        "coreVersion": "13.351",
        "systemId": "pirateborg",
        "systemVersion": "v1.1.5",
        "lastModifiedBy": null
      },
      "_key": "!tables.results!XDJE2uGyTQjH3yGi.HHp97nAw811hhyRt"
    },
    {
      "range": [
        2,
        2
      ],
      "description": "Pegasus",
      "_id": "KJ7Em9D49lGnTPhX",
      "type": "text",
      "name": "",
      "img": null,
      "weight": 1,
      "drawn": false,
      "flags": {},
      "_stats": {
        "compendiumSource": null,
        "duplicateSource": null,
        "exportSource": null,
        "coreVersion": "13.351",
        "systemId": "pirateborg",
        "systemVersion": "v1.1.5",
        "lastModifiedBy": null
      },
      "_key": "!tables.results!XDJE2uGyTQjH3yGi.KJ7Em9D49lGnTPhX"
    },
    {
      "range": [
        3,
        3
      ],
      "description": "Gorgone",
      "_id": "0OtwEc6zUUcPOAEc",
      "type": "text",
      "name": "",
      "img": null,
      "weight": 1,
      "drawn": false,
      "flags": {},
      "_stats": {
        "compendiumSource": null,
        "duplicateSource": null,
        "exportSource": null,
        "coreVersion": "13.351",
        "systemId": "pirateborg",
        "systemVersion": "v1.1.5",
        "lastModifiedBy": null
      },
      "_key": "!tables.results!XDJE2uGyTQjH3yGi.0OtwEc6zUUcPOAEc"
    },
    {
      "range": [
        4,
        4
      ],
      "description": "Medusa",
      "_id": "fImOV2TroYdLKO8S",
      "type": "text",
      "name": "",
      "img": null,
      "weight": 1,
      "drawn": false,
      "flags": {},
      "_stats": {
        "compendiumSource": null,
        "duplicateSource": null,
        "exportSource": null,
        "coreVersion": "13.351",
        "systemId": "pirateborg",
        "systemVersion": "v1.1.5",
        "lastModifiedBy": null
      },
      "_key": "!tables.results!XDJE2uGyTQjH3yGi.fImOV2TroYdLKO8S"
    },
    {
      "range": [
        5,
        5
      ],
      "description": "Cycloop",
      "_id": "G4MqSyWXgrKp6WZ2",
      "type": "text",
      "name": "",
      "img": null,
      "weight": 1,
      "drawn": false,
      "flags": {},
      "_stats": {
        "compendiumSource": null,
        "duplicateSource": null,
        "exportSource": null,
        "coreVersion": "13.351",
        "systemId": "pirateborg",
        "systemVersion": "v1.1.5",
        "lastModifiedBy": null
      },
      "_key": "!tables.results!XDJE2uGyTQjH3yGi.G4MqSyWXgrKp6WZ2"
    },
    {
      "range": [
        6,
        6
      ],
      "description": "Sater",
      "_id": "zlu1L1MnW0QpPNop",
      "type": "text",
      "name": "",
      "img": null,
      "weight": 1,
      "drawn": false,
      "flags": {},
      "_stats": {
        "compendiumSource": null,
        "duplicateSource": null,
        "exportSource": null,
        "coreVersion": "13.351",
        "systemId": "pirateborg",
        "systemVersion": "v1.1.5",
        "lastModifiedBy": null
      },
      "_key": "!tables.results!XDJE2uGyTQjH3yGi.zlu1L1MnW0QpPNop"
    },
    {
      "range": [
        7,
        7
      ],
      "description": "Nimf",
      "_id": "rnhLZzaQgJjz7j7u",
      "type": "text",
      "name": "",
      "img": null,
      "weight": 1,
      "drawn": false,
      "flags": {},
      "_stats": {
        "compendiumSource": null,
        "duplicateSource": null,
        "exportSource": null,
        "coreVersion": "13.351",
        "systemId": "pirateborg",
        "systemVersion": "v1.1.5",
        "lastModifiedBy": null
      },
      "_key": "!tables.results!XDJE2uGyTQjH3yGi.rnhLZzaQgJjz7j7u"
    },
    {
      "range": [
        8,
        8
      ],
      "description": "Nereïde",
      "_id": "g3UC35sd5xd3rfNR",
      "type": "text",
      "name": "",
      "img": null,
      "weight": 1,
      "drawn": false,
      "flags": {},
      "_stats": {
        "compendiumSource": null,
        "duplicateSource": null,
        "exportSource": null,
        "coreVersion": "13.351",
        "systemId": "pirateborg",
        "systemVersion": "v1.1.5",
        "lastModifiedBy": null
      },
      "_key": "!tables.results!XDJE2uGyTQjH3yGi.g3UC35sd5xd3rfNR"
    }
  ],
  "_id": "XDJE2uGyTQjH3yGi",
  "img": "icons/svg/d20-grey.svg",
  "replacement": true,
  "displayRoll": true,
  "folder": "KiYlWlGiw4pVcf3n",
  "flags": {},
  "_stats": {
    "compendiumSource": null,
    "duplicateSource": null,
    "exportSource": null,
    "coreVersion": "13.351",
    "systemId": "pirateborg",
    "systemVersion": "v1.1.5",
    "createdTime": 1767298042182,
    "modifiedTime": 1767298042182,
    "lastModifiedBy": "uoZc4xjiPYKnclmd"
  },
  "ownership": {
    "default": 0,
    "uoZc4xjiPYKnclmd": 3
  },
  "sort": 0,
  "_key": "!tables!XDJE2uGyTQjH3yGi"
}
