{
  "name": "Dutch Merchant Ship Names from Mythology (Creatures)",
  "formula": "1d10",
  "description": "",
  "results": [
    {
      "range": [
        1,
        1
      ],
      "description": "Wyvern",
      "_id": "pGBG1FBhX2KNhhUu",
      "type": "text",
      "name": "",
      "img": null,
      "weight": 1,
      "drawn": false,
      "flags": {},
      "_stats": {
        "compendiumSource": null,
        "duplicateSource": null,
        "exportSource": null,
        "coreVersion": "13.351",
        "systemId": "pirateborg",
        "systemVersion": "v1.1.5",
        "lastModifiedBy": null
      },
      "_key": "!tables.results!jnrjLffLa1CT5OXa.pGBG1FBhX2KNhhUu"
    },
    {
      "range": [
        2,
        2
      ],
      "description": "Chimaera",
      "_id": "zEGsRaVbAirtibfH",
      "type": "text",
      "name": "",
      "img": null,
      "weight": 1,
      "drawn": false,
      "flags": {},
      "_stats": {
        "compendiumSource": null,
        "duplicateSource": null,
        "exportSource": null,
        "coreVersion": "13.351",
        "systemId": "pirateborg",
        "systemVersion": "v1.1.5",
        "lastModifiedBy": null
      },
      "_key": "!tables.results!jnrjLffLa1CT5OXa.zEGsRaVbAirtibfH"
    },
    {
      "range": [
        3,
        3
      ],
      "description": "Griffioen",
      "_id": "R4XlB0ioNDc5Dqea",
      "type": "text",
      "name": "",
      "img": null,
      "weight": 1,
      "drawn": false,
      "flags": {},
      "_stats": {
        "compendiumSource": null,
        "duplicateSource": null,
        "exportSource": null,
        "coreVersion": "13.351",
        "systemId": "pirateborg",
        "systemVersion": "v1.1.5",
        "lastModifiedBy": null
      },
      "_key": "!tables.results!jnrjLffLa1CT5OXa.R4XlB0ioNDc5Dqea"
    },
    {
      "range": [
        4,
        4
      ],
      "description": "Hippogrief",
      "_id": "5x2ccFeYT8E8g3o7",
      "type": "text",
      "name": "",
      "img": null,
      "weight": 1,
      "drawn": false,
      "flags": {},
      "_stats": {
        "compendiumSource": null,
        "duplicateSource": null,
        "exportSource": null,
        "coreVersion": "13.351",
        "systemId": "pirateborg",
        "systemVersion": "v1.1.5",
        "lastModifiedBy": null
      },
      "_key": "!tables.results!jnrjLffLa1CT5OXa.5x2ccFeYT8E8g3o7"
    },
    {
      "range": [
        5,
        5
      ],
      "description": "Manticore",
      "_id": "2lSpDidwd4avGm4S",
      "type": "text",
      "name": "",
      "img": null,
      "weight": 1,
      "drawn": false,
      "flags": {},
      "_stats": {
        "compendiumSource": null,
        "duplicateSource": null,
        "exportSource": null,
        "coreVersion": "13.351",
        "systemId": "pirateborg",
        "systemVersion": "v1.1.5",
        "lastModifiedBy": null
      },
      "_key": "!tables.results!jnrjLffLa1CT5OXa.2lSpDidwd4avGm4S"
    },
    {
      "range": [
        6,
        6
      ],
      "description": "Eenhoorn",
      "_id": "tnOPECQfVeJIIBe3",
      "type": "text",
      "name": "",
      "img": null,
      "weight": 1,
      "drawn": false,
      "flags": {},
      "_stats": {
        "compendiumSource": null,
        "duplicateSource": null,
        "exportSource": null,
        "coreVersion": "13.351",
        "systemId": "pirateborg",
        "systemVersion": "v1.1.5",
        "lastModifiedBy": null
      },
      "_key": "!tables.results!jnrjLffLa1CT5OXa.tnOPECQfVeJIIBe3"
    },
    {
      "range": [
        7,
        7
      ],
      "description": "Feniks",
      "_id": "pcSzMOQ3rjjl9ihy",
      "type": "text",
      "name": "",
      "img": null,
      "weight": 1,
      "drawn": false,
      "flags": {},
      "_stats": {
        "compendiumSource": null,
        "duplicateSource": null,
        "exportSource": null,
        "coreVersion": "13.351",
        "systemId": "pirateborg",
        "systemVersion": "v1.1.5",
        "lastModifiedBy": null
      },
      "_key": "!tables.results!jnrjLffLa1CT5OXa.pcSzMOQ3rjjl9ihy"
    },
    {
      "range": [
        8,
        8
      ],
      "description": "Yale",
      "_id": "PRY7WiYV0YgruD30",
      "type": "text",
      "name": "",
      "img": null,
      "weight": 1,
      "drawn": false,
      "flags": {},
      "_stats": {
        "compendiumSource": null,
        "duplicateSource": null,
        "exportSource": null,
        "coreVersion": "13.351",
        "systemId": "pirateborg",
        "systemVersion": "v1.1.5",
        "lastModifiedBy": null
      },
      "_key": "!tables.results!jnrjLffLa1CT5OXa.PRY7WiYV0YgruD30"
    },
    {
      "range": [
        9,
        9
      ],
      "description": "Zeemeermin",
      "_id": "jl5qoeP5Z9PA3CtZ",
      "type": "text",
      "name": "",
      "img": null,
      "weight": 1,
      "drawn": false,
      "flags": {},
      "_stats": {
        "compendiumSource": null,
        "duplicateSource": null,
        "exportSource": null,
        "coreVersion": "13.351",
        "systemId": "pirateborg",
        "systemVersion": "v1.1.5",
        "lastModifiedBy": null
      },
      "_key": "!tables.results!jnrjLffLa1CT5OXa.jl5qoeP5Z9PA3CtZ"
    },
    {
      "range": [
        10,
        10
      ],
      "description": "Triton",
      "_id": "qHCfeUrWcjYKu6zj",
      "type": "text",
      "name": "",
      "img": null,
      "weight": 1,
      "drawn": false,
      "flags": {},
      "_stats": {
        "compendiumSource": null,
        "duplicateSource": null,
        "exportSource": null,
        "coreVersion": "13.351",
        "systemId": "pirateborg",
        "systemVersion": "v1.1.5",
        "lastModifiedBy": null
      },
      "_key": "!tables.results!jnrjLffLa1CT5OXa.qHCfeUrWcjYKu6zj"
    }
  ],
  "_id": "jnrjLffLa1CT5OXa",
  "img": "icons/svg/d20-grey.svg",
  "replacement": true,
  "displayRoll": true,
  "folder": "KiYlWlGiw4pVcf3n",
  "flags": {},
  "_stats": {
    "compendiumSource": null,
    "duplicateSource": null,
    "exportSource": null,
    "coreVersion": "13.351",
    "systemId": "pirateborg",
    "systemVersion": "v1.1.5",
    "createdTime": 1767298042182,
    "modifiedTime": 1767298042182,
    "lastModifiedBy": "uoZc4xjiPYKnclmd"
  },
  "ownership": {
    "default": 0,
    "uoZc4xjiPYKnclmd": 3
  },
  "sort": 0,
  "_key": "!tables!jnrjLffLa1CT5OXa"
}
