{
  "folder": "dcGDAIaexmTc4VzQ",
  "name": "Pirate Ship Names",
  "_id": "MEYUPtE2M01y04n4",
  "img": "icons/svg/d20-grey.svg",
  "description": "",
  "results": [
    {
      "type": "document",
      "weight": 1,
      "range": [
        2,
        2
      ],
      "name": "Pirate Ship Names: Jacobite Names",
      "img": "icons/svg/d20-grey.svg",
      "documentUuid": "Compendium.revolutionary-piratenames.rolltables.RollTable.eS7OGuUQsma898qq",
      "_id": "sFWPYjw8PJrjfGdz",
      "description": "",
      "drawn": false,
      "flags": {},
      "_stats": {
        "compendiumSource": null,
        "duplicateSource": null,
        "exportSource": null,
        "coreVersion": "13.351",
        "systemId": "pirateborg",
        "systemVersion": "v1.1.5",
        "createdTime": 1767302374328,
        "modifiedTime": 1767302374328,
        "lastModifiedBy": "uoZc4xjiPYKnclmd"
      },
      "_key": "!tables.results!MEYUPtE2M01y04n4.sFWPYjw8PJrjfGdz"
    },
    {
      "type": "document",
      "weight": 1,
      "range": [
        3,
        3
      ],
      "name": "Pirate Ship Names: Gallows Humor",
      "img": "icons/svg/d20-grey.svg",
      "documentUuid": "Compendium.revolutionary-piratenames.rolltables.RollTable.H2DYFrkBO4jgit9H",
      "_id": "0KxDZbmA3VhNDrWT",
      "description": "",
      "drawn": false,
      "flags": {},
      "_stats": {
        "compendiumSource": null,
        "duplicateSource": null,
        "exportSource": null,
        "coreVersion": "13.351",
        "systemId": "pirateborg",
        "systemVersion": "v1.1.5",
        "createdTime": 1767302379006,
        "modifiedTime": 1767302379006,
        "lastModifiedBy": "uoZc4xjiPYKnclmd"
      },
      "_key": "!tables.results!MEYUPtE2M01y04n4.0KxDZbmA3VhNDrWT"
    },
    {
      "type": "document",
      "weight": 1,
      "range": [
        4,
        4
      ],
      "name": "Pirate Ship Names: Aspirational",
      "img": "icons/svg/d20-grey.svg",
      "documentUuid": "Compendium.revolutionary-piratenames.rolltables.RollTable.fNquqRRIg94m5ZTF",
      "_id": "r0yFGEwHr6juTaP5",
      "description": "",
      "drawn": false,
      "flags": {},
      "_stats": {
        "compendiumSource": null,
        "duplicateSource": null,
        "exportSource": null,
        "coreVersion": "13.351",
        "systemId": "pirateborg",
        "systemVersion": "v1.1.5",
        "createdTime": 1767302420229,
        "modifiedTime": 1767302420229,
        "lastModifiedBy": "uoZc4xjiPYKnclmd"
      },
      "_key": "!tables.results!MEYUPtE2M01y04n4.r0yFGEwHr6juTaP5"
    },
    {
      "type": "document",
      "weight": 1,
      "range": [
        5,
        5
      ],
      "name": "Pirate Ship Names: Revenge",
      "img": "icons/svg/d20-grey.svg",
      "documentUuid": "Compendium.revolutionary-piratenames.rolltables.RollTable.1F9ANdIcboISGMWN",
      "_id": "OUEoeTWQv7pPndTG",
      "description": "",
      "drawn": false,
      "flags": {},
      "_stats": {
        "compendiumSource": null,
        "duplicateSource": null,
        "exportSource": null,
        "coreVersion": "13.351",
        "systemId": "pirateborg",
        "systemVersion": "v1.1.5",
        "createdTime": 1767302431299,
        "modifiedTime": 1767302431299,
        "lastModifiedBy": "uoZc4xjiPYKnclmd"
      },
      "_key": "!tables.results!MEYUPtE2M01y04n4.OUEoeTWQv7pPndTG"
    },
    {
      "type": "document",
      "weight": 1,
      "range": [
        6,
        6
      ],
      "name": "Pirate Ship Names: Animals",
      "img": "icons/svg/d20-grey.svg",
      "documentUuid": "Compendium.revolutionary-piratenames.rolltables.RollTable.VXn2g6gfF6Roc3CC",
      "_id": "hKCDpee4cACvMxXZ",
      "description": "",
      "drawn": false,
      "flags": {},
      "_stats": {
        "compendiumSource": null,
        "duplicateSource": null,
        "exportSource": null,
        "coreVersion": "13.351",
        "systemId": "pirateborg",
        "systemVersion": "v1.1.5",
        "createdTime": 1767302438995,
        "modifiedTime": 1767302438995,
        "lastModifiedBy": "uoZc4xjiPYKnclmd"
      },
      "_key": "!tables.results!MEYUPtE2M01y04n4.hKCDpee4cACvMxXZ"
    },
    {
      "type": "document",
      "weight": 1,
      "range": [
        7,
        7
      ],
      "name": "Pirate Ship Names: Threats",
      "img": "icons/svg/d20-grey.svg",
      "documentUuid": "Compendium.revolutionary-piratenames.rolltables.RollTable.9B2e0bf9Yy59hLTw",
      "_id": "NSn57iX9UHA5T4Ww",
      "description": "",
      "drawn": false,
      "flags": {},
      "_stats": {
        "compendiumSource": null,
        "duplicateSource": null,
        "exportSource": null,
        "coreVersion": "13.351",
        "systemId": "pirateborg",
        "systemVersion": "v1.1.5",
        "createdTime": 1767302443312,
        "modifiedTime": 1767302443312,
        "lastModifiedBy": "uoZc4xjiPYKnclmd"
      },
      "_key": "!tables.results!MEYUPtE2M01y04n4.NSn57iX9UHA5T4Ww"
    },
    {
      "type": "document",
      "weight": 1,
      "range": [
        8,
        8
      ],
      "name": "Pirate Ship Names: Blasphemous Names",
      "img": "icons/svg/d20-grey.svg",
      "documentUuid": "Compendium.revolutionary-piratenames.rolltables.RollTable.4DLfLbxviMHQm0RX",
      "_id": "ssLLuAnzwIBN0Zpv",
      "description": "",
      "drawn": false,
      "flags": {},
      "_stats": {
        "compendiumSource": null,
        "duplicateSource": null,
        "exportSource": null,
        "coreVersion": "13.351",
        "systemId": "pirateborg",
        "systemVersion": "v1.1.5",
        "createdTime": 1767302447286,
        "modifiedTime": 1767302447286,
        "lastModifiedBy": "uoZc4xjiPYKnclmd"
      },
      "_key": "!tables.results!MEYUPtE2M01y04n4.ssLLuAnzwIBN0Zpv"
    }
  ],
  "replacement": true,
  "displayRoll": true,
  "sort": 0,
  "ownership": {
    "default": 0,
    "uoZc4xjiPYKnclmd": 3
  },
  "flags": {},
  "_stats": {
    "compendiumSource": null,
    "duplicateSource": null,
    "exportSource": null,
    "coreVersion": "13.351",
    "systemId": "pirateborg",
    "systemVersion": "v1.1.5",
    "createdTime": 1767302366170,
    "modifiedTime": 1767302468356,
    "lastModifiedBy": "uoZc4xjiPYKnclmd"
  },
  "formula": "2d4",
  "_key": "!tables!MEYUPtE2M01y04n4"
}
