{
  "name": "Spanish Merchant Ship Names from Roman Mythology",
  "_id": "kJvfxBKO5gV8fbuJ",
  "img": "icons/svg/d20-grey.svg",
  "description": "",
  "results": [
    {
      "type": "document",
      "weight": 7,
      "range": [
        1,
        7
      ],
      "name": "Spanish Merchant Ship Names from Roman Mythology (Gods)",
      "img": "icons/svg/d20-grey.svg",
      "documentUuid": "RollTable.yYBEXTbAJkOcZ62P",
      "_id": "rjTm0J1qDSh6dIax",
      "description": "",
      "drawn": false,
      "flags": {},
      "_stats": {
        "compendiumSource": null,
        "duplicateSource": null,
        "exportSource": null,
        "coreVersion": "13.351",
        "systemId": "pirateborg",
        "systemVersion": "v1.1.5",
        "lastModifiedBy": null
      },
      "_key": "!tables.results!kJvfxBKO5gV8fbuJ.rjTm0J1qDSh6dIax"
    },
    {
      "type": "document",
      "weight": 5,
      "range": [
        8,
        12
      ],
      "name": "Spanish Merchant Ship Names from Roman Mythology (Heroes)",
      "img": "icons/svg/d20-grey.svg",
      "documentUuid": "RollTable.WzJTMr9uHGWaPbRw",
      "_id": "rUEIwhfpO8sqH2Rv",
      "description": "",
      "drawn": false,
      "flags": {},
      "_stats": {
        "compendiumSource": null,
        "duplicateSource": null,
        "exportSource": null,
        "coreVersion": "13.351",
        "systemId": "pirateborg",
        "systemVersion": "v1.1.5",
        "lastModifiedBy": null
      },
      "_key": "!tables.results!kJvfxBKO5gV8fbuJ.rUEIwhfpO8sqH2Rv"
    }
  ],
  "replacement": true,
  "displayRoll": true,
  "folder": "sKyGo9YBOLMQTvoO",
  "flags": {},
  "_stats": {
    "compendiumSource": null,
    "duplicateSource": null,
    "exportSource": null,
    "coreVersion": "13.351",
    "systemId": "pirateborg",
    "systemVersion": "v1.1.5",
    "createdTime": 1767298042182,
    "modifiedTime": 1767298042182,
    "lastModifiedBy": "uoZc4xjiPYKnclmd"
  },
  "formula": "1d12",
  "ownership": {
    "default": 0,
    "uoZc4xjiPYKnclmd": 3
  },
  "sort": 0,
  "_key": "!tables!kJvfxBKO5gV8fbuJ"
}
